consisid_eva_clip/__init__.py
consisid_eva_clip/bpe_simple_vocab_16e6.txt.gz
consisid_eva_clip/constants.py
consisid_eva_clip/eva_vit_model.py
consisid_eva_clip/factory.py
consisid_eva_clip/hf_configs.py
consisid_eva_clip/hf_model.py
consisid_eva_clip/loss.py
consisid_eva_clip/model.py
consisid_eva_clip/modified_resnet.py
consisid_eva_clip/openai.py
consisid_eva_clip/pretrained.py
consisid_eva_clip/rope.py
consisid_eva_clip/timm_model.py
consisid_eva_clip/tokenizer.py
consisid_eva_clip/transform.py
consisid_eva_clip/transformer.py
consisid_eva_clip/utils.py
consisid_eva_clip/model_configs/EVA01-CLIP-B-16.json
consisid_eva_clip/model_configs/EVA01-CLIP-g-14-plus.json
consisid_eva_clip/model_configs/EVA01-CLIP-g-14.json
consisid_eva_clip/model_configs/EVA02-CLIP-B-16.json
consisid_eva_clip/model_configs/EVA02-CLIP-L-14-336.json
consisid_eva_clip/model_configs/EVA02-CLIP-L-14.json
consisid_eva_clip/model_configs/EVA02-CLIP-bigE-14-plus.json
consisid_eva_clip/model_configs/EVA02-CLIP-bigE-14.json
consisid_eva_clip-1.0.2.dist-info/LICENSE
consisid_eva_clip-1.0.2.dist-info/METADATA
consisid_eva_clip-1.0.2.dist-info/WHEEL
consisid_eva_clip-1.0.2.dist-info/top_level.txt
consisid_eva_clip-1.0.2.dist-info/RECORD
