Metadata-Version: 2.1
Name: consisid_eva_clip
Version: 1.0.2
Summary: Identity-Preserving Text-to-Video Generation by Frequency Decomposition
Project-URL: Homepage, https://pku-yuangroup.github.io/ConsisID
Project-URL: Bug Tracker, https://github.com/PKU-YuanGroup/ConsisID/issues
Classifier: Programming Language :: Python :: 3
Classifier: License :: OSI Approved :: Apache Software License
Requires-Python: >=3.9
License-File: LICENSE
Requires-Dist: regex>=2024.11.6
Requires-Dist: timm>=1.0.9
Requires-Dist: einops>=0.8.0
Requires-Dist: numpy>=1.26.4
Requires-Dist: ftfy>=6.3.1
Requires-Dist: huggingface-hub>=0.26.1
Requires-Dist: safetensors>=0.4.5
Requires-Dist: insightface>=0.7.3
Requires-Dist: facexlib>=0.3.0
Requires-Dist: pyfacer>=0.0.4
